MANIFEST.in
README.md
requirements.txt
setup.py
basement/__init__.py
basement/__main__.py
basement/config.py
basement/process.py
basement.egg-info/PKG-INFO
basement.egg-info/SOURCES.txt
basement.egg-info/dependency_links.txt
basement.egg-info/entry_points.txt
basement.egg-info/requires.txt
basement.egg-info/top_level.txt
basement/templates/app/.gitignore
basement/templates/app/MANIFEST.in
basement/templates/app/README.md
basement/templates/app/requirements-dev.txt
basement/templates/app/requirements.txt
basement/templates/app/setup.py.basement-template
basement/templates/app/tests/{{project-name}}/.gitkeep
basement/templates/app/{{project-name}}/__init__.py.basement-template
basement/templates/app/{{project-name}}/__main__.py.basement-template
basement/templates/basement.egg-info/PKG-INFO
basement/templates/basement.egg-info/SOURCES.txt
basement/templates/basement.egg-info/dependency_links.txt
basement/templates/basement.egg-info/entry_points.txt
basement/templates/basement.egg-info/requires.txt
basement/templates/basement.egg-info/top_level.txt
basement/templates/default/.gitignore
basement/templates/default/MANIFEST.in
basement/templates/default/README.md
basement/templates/default/requirements-dev.txt
basement/templates/default/requirements.txt
basement/templates/default/setup.py.basement-template
basement/templates/default/tests/{{project-name}}/.gitkeep
basement/templates/default/{{project-name}}/__init__.py.basement-template
basement/templates/default/{{project-name}}/{{project-name}}.py.basement-template
basement/templates/flask/.gitignore
basement/templates/flask/MANIFEST.in
basement/templates/flask/README.md
basement/templates/flask/requirements-dev.txt
basement/templates/flask/requirements.txt
basement/templates/flask/setup.py.basement-template
basement/templates/flask/tests/{{project-name}}/.gitkeep
basement/templates/flask/{{project-name}}/__init__.py.basement-template
basement/templates/flask/{{project-name}}/__main__.py.basement-template
basement/templates/flask/{{project-name}}/static/favicon.ico.basement-ignore
basement/templates/flask/{{project-name}}/templates/home.html.basement-ignore
basement/templates/flask/{{project-name}}/views/__init__.py.basement-template
basement/templates/flask/{{project-name}}/views/home.py.basement-template
basement/templates/simpleflask/.gitignore
basement/templates/simpleflask/MANIFEST.in
basement/templates/simpleflask/README.md
basement/templates/simpleflask/requirements-dev.txt
