Metadata-Version: 1.0
Name: basement
Version: 0.2.2
Summary: A python project scaffolding generator.
Home-page: https://github.com/Raynes/basement
Author: Anthony Grimes
Author-email: i@raynes.me
License: MIT
Platform: UNKNOWN
